pulumi_stack_utils/__init__.py
pulumi_stack_utils/stack_reference.py
pulumi_stack_utils/aws/__init__.py
pulumi_stack_utils/aws/autotag.py
pulumi_stack_utils-0.1.2.dist-info/LICENSE
pulumi_stack_utils-0.1.2.dist-info/METADATA
pulumi_stack_utils-0.1.2.dist-info/WHEEL
pulumi_stack_utils-0.1.2.dist-info/top_level.txt
pulumi_stack_utils-0.1.2.dist-info/RECORD
