Metadata-Version: 2.1
Name: pulumi-stack-utils
Version: 0.1.2
Summary: Utilities for working with Pulumi stacks
Author-email: James Arnold <james@rs21.io>
License: BSD-2-Clause
Project-URL: repository, https://github.com/rs21io/pulumi-stack-utils
Keywords: pulumi,iac
License-File: LICENSE
Requires-Dist: boto3
Requires-Dist: pulumi
Requires-Dist: pyyaml
Provides-Extra: dev
Requires-Dist: black ; extra == 'dev'
Requires-Dist: pylint ; extra == 'dev'
Requires-Dist: pytest ; extra == 'dev'
Requires-Dist: pytest-cov ; extra == 'dev'
Requires-Dist: pytest-pylint ; extra == 'dev'
